backend_shim.py
pants_build_wheel-0.0.2.dist-info/METADATA
pants_build_wheel-0.0.2.dist-info/WHEEL
pants_build_wheel-0.0.2.dist-info/top_level.txt
pants_build_wheel-0.0.2.dist-info/RECORD
